{"trial_id": "0084", "hyperparameters": {"space": [{"class_name": "Int", "config": {"name": "num_layers", "default": null, "conditions": [], "min_value": 2, "max_value": 4, "step": 1, "sampling": "linear"}}, {"class_name": "Choice", "config": {"name": "units_0", "default": 2, "conditions": [], "values": [2, 4, 8, 16, 32, 64, 128], "ordered": true}}, {"class_name": "Choice", "config": {"name": "units_1", "default": 2, "conditions": [], "values": [2, 4, 8, 16, 32, 64, 128], "ordered": true}}, {"class_name": "Int", "config": {"name": "encoding_units", "default": null, "conditions": [], "min_value": 2, "max_value": 9, "step": 1, "sampling": "linear"}}, {"class_name": "Float", "config": {"name": "l1_value", "default": 0.01, "conditions": [], "min_value": 0.005, "max_value": 0.05, "step": 0.001, "sampling": "linear"}}, {"class_name": "Choice", "config": {"name": "units_2", "default": 2, "conditions": [], "values": [2, 4, 8, 16, 32, 64, 128], "ordered": true}}, {"class_name": "Choice", "config": {"name": "units_3", "default": 2, "conditions": [], "values": [2, 4, 8, 16, 32, 64, 128], "ordered": true}}], "values": {"num_layers": 4, "units_0": 8, "units_1": 64, "encoding_units": 5, "l1_value": 0.027, "units_2": 8, "units_3": 16, "tuner/epochs": 50, "tuner/initial_epoch": 17, "tuner/bracket": 1, "tuner/round": 1, "tuner/trial_id": "0075"}}, "metrics": {"metrics": {"loss": {"direction": "min", "observations": [{"value": [0.06986989080905914], "step": 32}]}, "decoding_loss": {"direction": "min", "observations": [{"value": [0.004226774908602238], "step": 32}]}, "prediction_loss": {"direction": "min", "observations": [{"value": [0.6764371395111084], "step": 32}]}, "val_loss": {"direction": "min", "observations": [{"value": [0.0683990865945816], "step": 32}]}, "val_decoding_loss": {"direction": "min", "observations": [{"value": [0.0013658596435561776], "step": 32}]}, "val_prediction_loss": {"direction": "min", "observations": [{"value": [0.6892627477645874], "step": 32}]}}}, "score": 0.0683990865945816, "best_step": 32, "status": "COMPLETED", "message": null}